<?xml version="1.0" encoding="UTF-8"?><database>
    <element audit="true" db_object_id="5a2a78e997812110ceb67b771153afe9" extends="task" label="NeedIt" max_length="40" name="x_58872_needit_needit1" type="collection">
        <element default="true" label="Active" max_length="40" name="u_active" type="boolean"/>
        <element attributes="edge_encryption_enabled=true" choice="1" label="New Choice" max_length="40" name="u_choice_4" type="string">
            <choice>
                <element inactive_on_update="false" label="Choice 1" sequence="0" value="Choice 1"/>
                <element inactive_on_update="false" label="Choice 2" sequence="1" value="Choice 2"/>
                <element inactive_on_update="false" label="Choice 3" sequence="2" value="Choice 3"/>
            </choice>
        </element>
        <element attributes="edge_encryption_enabled=true" label="Created" max_length="40" name="u_created" type="glide_date_time"/>
        <element attributes="encode_utf8=false" label="Created By" max_length="32" name="u_created_by" reference="sys_user" type="reference"/>
        <element attributes="edge_encryption_enabled=true" label="Opened" mandatory="true" max_length="40" name="u_opened" type="glide_date_time"/>
        <element attributes="encode_utf8=false" label="Opened By" mandatory="true" max_length="32" name="u_opened_by" reference="sys_user" type="reference"/>
        <element attributes="encode_utf8=false" label="Requested for" mandatory="true" max_length="32" name="u_requested_for" reference="sys_user" type="reference"/>
        <element attributes="edge_encryption_enabled=true" choice="1" default="legal" label="Request type" mandatory="true" max_length="40" name="u_request_type" type="string">
            <choice>
                <element inactive="true" inactive_on_update="true" label="Choice 1" sequence="0" value="Choice 1"/>
                <element inactive_on_update="false" label="Human Resources" sequence="0" value="hr"/>
                <element inactive="true" inactive_on_update="true" label="Choice 2" sequence="1" value="Choice 2"/>
                <element inactive_on_update="false" label="Facilities" sequence="1" value="facilities"/>
                <element inactive="true" inactive_on_update="true" label="Choice 3" sequence="2" value="Choice 3"/>
                <element inactive_on_update="false" label="Legal" sequence="2" value="legal"/>
            </choice>
        </element>
        <element attributes="edge_encryption_enabled=true" label="Updated" max_length="40" name="u_updated" type="glide_date_time"/>
        <element attributes="encode_utf8=false" label="Updated By" max_length="32" name="u_updated_by" reference="sys_user" type="reference"/>
        <element attributes="edge_encryption_enabled=true" choice="1" default="legal1" label="What Needed" mandatory="true" max_length="40" name="u_what_needed" type="string">
            <choice>
                <element inactive_on_update="false" label="Human Resources 1" sequence="0" value="hr1"/>
                <element inactive_on_update="false" label="Human Resources 2" sequence="1" value="hr2"/>
                <element inactive_on_update="false" label="Facilities 1" sequence="2" value="facilities1"/>
                <element inactive_on_update="false" label="Facilities 2" sequence="3" value="facilities2"/>
                <element inactive_on_update="false" label="Legal 1" sequence="4" value="legal1"/>
                <element inactive_on_update="false" label="Legal 2" sequence="5" value="legal2"/>
            </choice>
        </element>
        <element attributes="edge_encryption_enabled=true" label="When Needed" mandatory="true" max_length="40" name="u_when_needed" type="glide_date_time"/>
    </element>
</database>
